YW_download/__init__.py
YW_download/functions.py
YW_download/run.py
YW_download-0.1.3.dist-info/METADATA
YW_download-0.1.3.dist-info/WHEEL
YW_download-0.1.3.dist-info/top_level.txt
YW_download-0.1.3.dist-info/RECORD
