Metadata-Version: 2.1
Name: YW_download
Version: 0.1.3
Summary: YWs downloading tool
Author: Yulun Wu
Author-email: yulunwu8@gmail.com
Classifier: Programming Language :: Python :: 3
Requires-Python: >=3.8
Requires-Dist: requests
Requires-Dist: pandas
Requires-Dist: numpy
